{"field_audio": "a38f99ea-d4cd-45c6-9ca9-33bf7325c422.wma", "_id": "56a456b4ef3c8213c800cb14", "field_text": "请客何在蜀双箸。", "field_annotations": [{"indices": [2, 3], "text": "何在", "explanation": "不在乎。"}, {"indices": [4, 5, 6], "text": "蜀双箸", "explanation": "（添）一双筷子，指多请 一个客人。"}], "field_source": {"metadata": "{\"page\": 73}", "source": {"_id": "56a456b2ef3c8213c800c944", "field_title": "《福州方言俗语歌谣》, 陈泽平, 1998, 福建人民出版社", "field_description": "陈泽平"}}, "field_notes": "中国的酒席是围圓桌而食的“聚餐”，而且酒菜总是多 得吃不完，临时多请个客人确实只需多摆下一双筷子就行。 何况说，多一个朋友多一条路。\n", "field_tags": ["为人处世", "谚语"]}