{"field_audio": "2d3fa69b-1aa1-42ed-af4a-4e01e1959f49.wma", "_id": "56a456b5ef3c8213c800cca2", "field_metaphor": "可笑的自夸。", "field_text": "亲母自耀骹腿白。", "field_annotations": [{"indices": [0, 1], "text": "亲母", "explanation": "亲家母。"}, {"indices": [2, 3], "text": "自耀", "explanation": "自夸。"}, {"indices": [4, 5], "text": "骹腿", "explanation": "腿。"}], "field_source": {"source": {"_id": "56a456b2ef3c8213c800c944", "field_title": "《福州方言俗语歌谣》, 陈泽平, 1998, 福建人民出版社", "field_description": "陈泽平"}}, "field_tags": ["惯用语"]}