{"field_audio": "ecfc04d7-daea-4c18-8b6c-d209d5510dd8.wma", "_id": "56a456b3ef3c8213c800c9e6", "field_text": "呆桃暮李，好食无对讲起。", "field_annotations": [{"indices": [0], "text": "呆", "explanation": "坏。"}, {"indices": [2], "text": "暮", "explanation": "（音）烂的"}, {"indices": [5, 6], "text": "好食", "explanation": "好吃。"}, {"indices": [7, 8, 9, 10], "text": "无对讲起", "explanation": "（好吃得）不知从何说起，无法形容。"}, {"indices": [8], "text": "对", "explanation": "（音）地方，处所。"}], "field_source": {"source": {"_id": "56a456b2ef3c8213c800c944", "field_title": "《福州方言俗语歌谣》, 陈泽平, 1998, 福建人民出版社", "field_description": "陈泽平"}, "metadata": "{\"page\": 35}"}, "field_notes": "不怕腹泻，不妨试试烂桃烂李子的滋味如何。", "field_tags": ["物产美食", "谚语"]}