{"field_audio": "10f03227-1727-4608-9a3b-e1eb0667dda5.wma", "_id": "56a456b6ef3c8213c800cd55", "field_metaphor": "谁也不比谁强。", "field_text": "眠床下踢毽——平平悬。", "field_annotations": [{"indices": [0, 1], "text": "眠床", "explanation": "床。"}, {"indices": [7, 8], "text": "平平", "explanation": "一样，同样。"}, {"indices": [9], "text": "悬", "explanation": "高；俗写同音字“咸”。"}], "field_source": {"source": {"_id": "56a456b2ef3c8213c800c944", "field_title": "《福州方言俗语歌谣》, 陈泽平, 1998, 福建人民出版社", "field_description": "陈泽平"}, "metadata": "{\"page\": 144}"}, "field_tags": ["歇后语", "双关类"]}