{"field_audio": "b1f6af70-9cde-4503-97dc-387c02a14032.wma", "_id": "56a456b3ef3c8213c800ca6e", "field_text": "桌悬讨侬嫌。", "field_annotations": [{"indices": [1], "text": "悬", "explanation": "高；俗写同音的“咸”字。"}, {"indices": [2, 3, 4], "text": "讨侬嫌", "explanation": "招人讨厌。"}], "field_source": {"source": {"_id": "56a456b2ef3c8213c800c944", "field_title": "《福州方言俗语歌谣》, 陈泽平, 1998, 福建人民出版社", "field_description": "陈泽平"}, "metadata": "{\"page\": 52}"}, "field_notes": "孩子长到桌子那么高时，就越来越顽皮了。", "field_tags": ["家庭生活", "谚语"]}